marimo_chem_utils/__init__.py
marimo_chem_utils/core.py
marimo_chem_utils-0.2.4.dist-info/licenses/LICENSE
marimo_chem_utils-0.2.4.dist-info/METADATA
marimo_chem_utils-0.2.4.dist-info/WHEEL
marimo_chem_utils-0.2.4.dist-info/top_level.txt
marimo_chem_utils-0.2.4.dist-info/RECORD
