Metadata-Version: 2.4
Name: marimo-chem-utils
Version: 0.2.4
Summary: A collection of cheminformatics utility functions for use with marimo notebooks.
Requires-Python: >=3.11
License-File: LICENSE
Requires-Dist: marimo>=0.18.3
Requires-Dist: pandas>=2.3.3
Requires-Dist: rdkit>=2025.9.3
Requires-Dist: scikit-learn>=1.7.2
Requires-Dist: useful-rdkit-utils==0.96
Requires-Dist: altair>=5.3.0
Provides-Extra: test
Requires-Dist: pytest; extra == "test"
Dynamic: license-file
